url_analyzer/__init__.py
py_url_analyzer-0.0.2.dist-info/LICENSE
py_url_analyzer-0.0.2.dist-info/METADATA
py_url_analyzer-0.0.2.dist-info/WHEEL
py_url_analyzer-0.0.2.dist-info/top_level.txt
py_url_analyzer-0.0.2.dist-info/RECORD
