Metadata-Version: 2.1
Name: py-url-analyzer
Version: 0.0.2
Summary: A simple URL analyzer
Home-page: https://github.com/seu-usuario/seu-projeto
Author: Lucas Andrade
Author-email: lafdesouza2002@gmail.com
Classifier: Programming Language :: Python :: 3
Classifier: License :: OSI Approved :: MIT License
Classifier: Operating System :: OS Independent
License-File: LICENSE
Requires-Dist: beautifulsoup4
Requires-Dist: certifi
Requires-Dist: charset-normalizer
Requires-Dist: idna
Requires-Dist: requests
Requires-Dist: soupsieve
Requires-Dist: urllib3
